arkiv_sdk/__init__.py
arkiv_sdk/constants.py
arkiv_sdk/py.typed
arkiv_sdk/types.py
arkiv_sdk/utils.py
arkiv_sdk/wallet.py
arkiv_sdk-0.2.1.dist-info/licenses/LICENSE
arkiv_sdk-0.2.1.dist-info/WHEEL
arkiv_sdk-0.2.1.dist-info/METADATA
arkiv_sdk-0.2.1.dist-info/RECORD
