Metadata-Version: 2.4
Name: arkiv-sdk
Version: 0.2.1
Summary: Arkiv Python SDK.
Author-email: rvdp <online@well-founded.dev>
Requires-Python: >=3.10
License-Expression: GPL-3.0-only
License-File: LICENSE
Requires-Dist: anyio>=4.10.0
Requires-Dist: pyxdg>=0.28
Requires-Dist: rlp>=1.2.0
Requires-Dist: web3>=7.0.0
Project-URL: Documentation, https://arkiv-network.github.io/arkiv-sdk-python/arkiv_sdk.html
Project-URL: Homepage, https://github.com/Arkiv-Network/
Project-URL: Issues, https://github.com/Arkiv-Network/arkiv-sdk-python/issues
Project-URL: Repository, https://github.com/Arkiv-Network/arkiv-sdk-python
